pyflantic-0.1.0.dist-info/METADATA
pyflantic-0.1.0.dist-info/WHEEL
pyflantic-0.1.0.dist-info/licenses/LICENSE.txt
pyflantic/__init__.py
pyflantic/checker.py
pyflantic/log.py
pyflantic-0.1.0.dist-info/RECORD
